{
  "version": "5",
  "dialect": "sqlite",
  "id": "b01673c2-646e-4e38-b432-ace0ae61c816",
  "prevId": "86c815b3-8772-4db0-b25d-c52dff63ce1f",
  "tables": {
    "email_verification_codes": {
      "name": "email_verification_codes",
      "columns": {
        "code": {
          "name": "code",
          "type": "text",
          "primaryKey": true,
          "notNull": true,
          "autoincrement": false
        },
        "verified_at": {
          "name": "verified_at",
          "type": "text",
          "primaryKey": false,
          "notNull": true,
          "autoincrement": false,
          "default": "(CURRENT_TIMESTAMP)"
        },
        "user_id": {
          "name": "user_id",
          "type": "integer",
          "primaryKey": false,
          "notNull": true,
          "autoincrement": false
        }
      },
      "indexes": {},
      "foreignKeys": {
        "email_verification_codes_user_id_users_id_fk": {
          "name": "email_verification_codes_user_id_users_id_fk",
          "tableFrom": "email_verification_codes",
          "tableTo": "users",
          "columnsFrom": [
            "user_id"
          ],
          "columnsTo": [
            "id"
          ],
          "onDelete": "cascade",
          "onUpdate": "cascade"
        }
      },
      "compositePrimaryKeys": {},
      "uniqueConstraints": {}
    },
    "external_identities": {
      "name": "external_identities",
      "columns": {
        "id": {
          "name": "id",
          "type": "text",
          "primaryKey": true,
          "notNull": true,
          "autoincrement": false
        },
        "email": {
          "name": "email",
          "type": "text",
          "primaryKey": false,
          "notNull": true,
          "autoincrement": false
        },
        "provider": {
          "name": "provider",
          "type": "text",
          "primaryKey": false,
          "notNull": true,
          "autoincrement": false
        },
        "user_id": {
          "name": "user_id",
          "type": "integer",
          "primaryKey": false,
          "notNull": true,
          "autoincrement": false
        }
      },
      "indexes": {},
      "foreignKeys": {
        "external_identities_user_id_users_id_fk": {
          "name": "external_identities_user_id_users_id_fk",
          "tableFrom": "external_identities",
          "tableTo": "users",
          "columnsFrom": [
            "user_id"
          ],
          "columnsTo": [
            "id"
          ],
          "onDelete": "cascade",
          "onUpdate": "cascade"
        }
      },
      "compositePrimaryKeys": {},
      "uniqueConstraints": {}
    },
    "jobs": {
      "name": "jobs",
      "columns": {
        "id": {
          "name": "id",
          "type": "integer",
          "primaryKey": true,
          "notNull": true,
          "autoincrement": true
        },
        "job": {
          "name": "job",
          "type": "text",
          "primaryKey": false,
          "notNull": true,
          "autoincrement": false
        }
      },
      "indexes": {
        "jobs_job_unique": {
          "name": "jobs_job_unique",
          "columns": [
            "job"
          ],
          "isUnique": true
        }
      },
      "foreignKeys": {},
      "compositePrimaryKeys": {},
      "uniqueConstraints": {}
    },
    "user_profile_jobs": {
      "name": "user_profile_jobs",
      "columns": {
        "user_id": {
          "name": "user_id",
          "type": "integer",
          "primaryKey": false,
          "notNull": true,
          "autoincrement": false
        },
        "job_id": {
          "name": "job_id",
          "type": "integer",
          "primaryKey": false,
          "notNull": true,
          "autoincrement": false
        }
      },
      "indexes": {},
      "foreignKeys": {
        "user_profile_jobs_user_id_user_profiles_id_fk": {
          "name": "user_profile_jobs_user_id_user_profiles_id_fk",
          "tableFrom": "user_profile_jobs",
          "tableTo": "user_profiles",
          "columnsFrom": [
            "user_id"
          ],
          "columnsTo": [
            "id"
          ],
          "onDelete": "cascade",
          "onUpdate": "cascade"
        },
        "user_profile_jobs_job_id_jobs_id_fk": {
          "name": "user_profile_jobs_job_id_jobs_id_fk",
          "tableFrom": "user_profile_jobs",
          "tableTo": "jobs",
          "columnsFrom": [
            "job_id"
          ],
          "columnsTo": [
            "id"
          ],
          "onDelete": "cascade",
          "onUpdate": "cascade"
        }
      },
      "compositePrimaryKeys": {
        "user_profile_jobs_job_id_user_id_pk": {
          "columns": [
            "job_id",
            "user_id"
          ],
          "name": "user_profile_jobs_job_id_user_id_pk"
        }
      },
      "uniqueConstraints": {}
    },
    "user_profiles": {
      "name": "user_profiles",
      "columns": {
        "id": {
          "name": "id",
          "type": "integer",
          "primaryKey": true,
          "notNull": true,
          "autoincrement": false
        },
        "nickname": {
          "name": "nickname",
          "type": "text",
          "primaryKey": false,
          "notNull": true,
          "autoincrement": false
        },
        "date_of_birth_year": {
          "name": "date_of_birth_year",
          "type": "integer",
          "primaryKey": false,
          "notNull": true,
          "autoincrement": false
        },
        "created_at": {
          "name": "created_at",
          "type": "text",
          "primaryKey": false,
          "notNull": true,
          "autoincrement": false,
          "default": "(CURRENT_TIMESTAMP)"
        },
        "updated_at": {
          "name": "updated_at",
          "type": "text",
          "primaryKey": false,
          "notNull": true,
          "autoincrement": false,
          "default": "(CURRENT_TIMESTAMP)"
        }
      },
      "indexes": {
        "user_profiles_nickname_unique": {
          "name": "user_profiles_nickname_unique",
          "columns": [
            "nickname"
          ],
          "isUnique": true
        }
      },
      "foreignKeys": {
        "user_profiles_id_users_id_fk": {
          "name": "user_profiles_id_users_id_fk",
          "tableFrom": "user_profiles",
          "tableTo": "users",
          "columnsFrom": [
            "id"
          ],
          "columnsTo": [
            "id"
          ],
          "onDelete": "no action",
          "onUpdate": "no action"
        }
      },
      "compositePrimaryKeys": {},
      "uniqueConstraints": {}
    },
    "users": {
      "name": "users",
      "columns": {
        "id": {
          "name": "id",
          "type": "integer",
          "primaryKey": true,
          "notNull": true,
          "autoincrement": true
        },
        "email": {
          "name": "email",
          "type": "text",
          "primaryKey": false,
          "notNull": true,
          "autoincrement": false
        },
        "created_at": {
          "name": "created_at",
          "type": "text",
          "primaryKey": false,
          "notNull": true,
          "autoincrement": false,
          "default": "(CURRENT_TIMESTAMP)"
        },
        "last_signed_in_at": {
          "name": "last_signed_in_at",
          "type": "text",
          "primaryKey": false,
          "notNull": true,
          "autoincrement": false,
          "default": "(CURRENT_TIMESTAMP)"
        }
      },
      "indexes": {
        "users_email_unique": {
          "name": "users_email_unique",
          "columns": [
            "email"
          ],
          "isUnique": true
        }
      },
      "foreignKeys": {},
      "compositePrimaryKeys": {},
      "uniqueConstraints": {}
    },
    "worries": {
      "name": "worries",
      "columns": {
        "id": {
          "name": "id",
          "type": "integer",
          "primaryKey": true,
          "notNull": true,
          "autoincrement": true
        },
        "worry": {
          "name": "worry",
          "type": "text",
          "primaryKey": false,
          "notNull": true,
          "autoincrement": false
        }
      },
      "indexes": {
        "worries_worry_unique": {
          "name": "worries_worry_unique",
          "columns": [
            "worry"
          ],
          "isUnique": true
        }
      },
      "foreignKeys": {},
      "compositePrimaryKeys": {},
      "uniqueConstraints": {}
    },
    "question_answers": {
      "name": "question_answers",
      "columns": {
        "id": {
          "name": "id",
          "type": "integer",
          "primaryKey": true,
          "notNull": true,
          "autoincrement": true
        },
        "answer": {
          "name": "answer",
          "type": "text",
          "primaryKey": false,
          "notNull": true,
          "autoincrement": false
        },
        "question_distribution_id": {
          "name": "question_distribution_id",
          "type": "integer",
          "primaryKey": false,
          "notNull": true,
          "autoincrement": false
        },
        "user_id": {
          "name": "user_id",
          "type": "integer",
          "primaryKey": false,
          "notNull": true,
          "autoincrement": false
        },
        "is_public": {
          "name": "is_public",
          "type": "integer",
          "primaryKey": false,
          "notNull": true,
          "autoincrement": false,
          "default": false
        },
        "created_at": {
          "name": "created_at",
          "type": "text",
          "primaryKey": false,
          "notNull": true,
          "autoincrement": false,
          "default": "(CURRENT_TIMESTAMP)"
        },
        "updated_at": {
          "name": "updated_at",
          "type": "text",
          "primaryKey": false,
          "notNull": true,
          "autoincrement": false,
          "default": "(CURRENT_TIMESTAMP)"
        }
      },
      "indexes": {
        "created_at_idx": {
          "name": "created_at_idx",
          "columns": [
            "created_at"
          ],
          "isUnique": false
        }
      },
      "foreignKeys": {
        "question_answers_question_distribution_id_question_distributions_id_fk": {
          "name": "question_answers_question_distribution_id_question_distributions_id_fk",
          "tableFrom": "question_answers",
          "tableTo": "question_distributions",
          "columnsFrom": [
            "question_distribution_id"
          ],
          "columnsTo": [
            "id"
          ],
          "onDelete": "set null",
          "onUpdate": "cascade"
        },
        "question_answers_user_id_users_id_fk": {
          "name": "question_answers_user_id_users_id_fk",
          "tableFrom": "question_answers",
          "tableTo": "users",
          "columnsFrom": [
            "user_id"
          ],
          "columnsTo": [
            "id"
          ],
          "onDelete": "cascade",
          "onUpdate": "cascade"
        }
      },
      "compositePrimaryKeys": {},
      "uniqueConstraints": {}
    },
    "question_distributions": {
      "name": "question_distributions",
      "columns": {
        "id": {
          "name": "id",
          "type": "integer",
          "primaryKey": true,
          "notNull": true,
          "autoincrement": true
        },
        "question_id": {
          "name": "question_id",
          "type": "integer",
          "primaryKey": false,
          "notNull": true,
          "autoincrement": false
        },
        "distribution_date": {
          "name": "distribution_date",
          "type": "text",
          "primaryKey": false,
          "notNull": true,
          "autoincrement": false,
          "default": "(CURRENT_DATE)"
        }
      },
      "indexes": {
        "question_distributions_distribution_date_unique": {
          "name": "question_distributions_distribution_date_unique",
          "columns": [
            "distribution_date"
          ],
          "isUnique": true
        }
      },
      "foreignKeys": {
        "question_distributions_question_id_questions_id_fk": {
          "name": "question_distributions_question_id_questions_id_fk",
          "tableFrom": "question_distributions",
          "tableTo": "questions",
          "columnsFrom": [
            "question_id"
          ],
          "columnsTo": [
            "id"
          ],
          "onDelete": "no action",
          "onUpdate": "no action"
        }
      },
      "compositePrimaryKeys": {},
      "uniqueConstraints": {}
    },
    "questions": {
      "name": "questions",
      "columns": {
        "id": {
          "name": "id",
          "type": "integer",
          "primaryKey": true,
          "notNull": true,
          "autoincrement": true
        },
        "question": {
          "name": "question",
          "type": "text",
          "primaryKey": false,
          "notNull": true,
          "autoincrement": false
        },
        "created_at": {
          "name": "created_at",
          "type": "text",
          "primaryKey": false,
          "notNull": true,
          "autoincrement": false,
          "default": "(CURRENT_TIMESTAMP)"
        },
        "updated_at": {
          "name": "updated_at",
          "type": "text",
          "primaryKey": false,
          "notNull": true,
          "autoincrement": false,
          "default": "(CURRENT_TIMESTAMP)"
        }
      },
      "indexes": {},
      "foreignKeys": {},
      "compositePrimaryKeys": {},
      "uniqueConstraints": {}
    }
  },
  "enums": {},
  "_meta": {
    "schemas": {},
    "tables": {},
    "columns": {}
  }
}